{
  "updatedAt": "08.06.2026 17:57:00",
  "signals": [
    {
      "ticker": "KCHOL",
      "alis": "191.20",
      "stop": "188.50",
      "risk": "1.41",
      "formation": "Harami",
      "current": null,
      "change": null,
      "grafikUrl": null
    },
    {
      "ticker": "SANKO",
      "alis": "22.62",
      "stop": "22.28",
      "risk": "1.50",
      "formation": "Harami",
      "current": null,
      "change": null,
      "grafikUrl": null
    },
    {
      "ticker": "MEDTR",
      "alis": "30.32",
      "stop": "29.84",
      "risk": "1.58",
      "formation": "Ters Çekiç",
      "current": null,
      "change": null,
      "grafikUrl": null
    },
    {
      "ticker": "RGYAS",
      "alis": "196.25",
      "stop": "193.10",
      "risk": "1.61",
      "formation": "Harami",
      "current": null,
      "change": null,
      "grafikUrl": null
    },
    {
      "ticker": "AYDEM",
      "alis": "25.92",
      "stop": "25.46",
      "risk": "1.77",
      "formation": "Harami",
      "current": null,
      "change": null,
      "grafikUrl": null
    },
    {
      "ticker": "PAHOL",
      "alis": "1.6700",
      "stop": "1.6400",
      "risk": "1.80",
      "formation": "Harami",
      "current": null,
      "change": null,
      "grafikUrl": null
    },
    {
      "ticker": "OYAKC",
      "alis": "21.02",
      "stop": "20.64",
      "risk": "1.81",
      "formation": "Harami",
      "current": null,
      "change": null,
      "grafikUrl": null
    },
    {
      "ticker": "ALVES",
      "alis": "2.7600",
      "stop": "2.7100",
      "risk": "1.81",
      "formation": "Doji",
      "current": null,
      "change": null,
      "grafikUrl": null
    },
    {
      "ticker": "ANGEN",
      "alis": "11.23",
      "stop": "11.02",
      "risk": "1.87",
      "formation": "Harami",
      "current": null,
      "change": null,
      "grafikUrl": null
    },
    {
      "ticker": "GRTHO",
      "alis": "209.45",
      "stop": "205.50",
      "risk": "1.89",
      "formation": "Harami",
      "current": null,
      "change": null,
      "grafikUrl": null
    },
    {
      "ticker": "APMDLF",
      "alis": "25.36",
      "stop": "24.87",
      "risk": "1.93",
      "formation": "Çekiç",
      "current": null,
      "change": null,
      "grafikUrl": null
    },
    {
      "ticker": "BIMAS",
      "alis": "377.75",
      "stop": "370.00",
      "risk": "2.05",
      "formation": "Harami",
      "current": null,
      "change": null,
      "grafikUrl": null
    },
    {
      "ticker": "ZOREN",
      "alis": "3.0650",
      "stop": "3.0000",
      "risk": "2.12",
      "formation": "Doji",
      "current": null,
      "change": null,
      "grafikUrl": null
    },
    {
      "ticker": "KGYO",
      "alis": "12.26",
      "stop": "11.99",
      "risk": "2.20",
      "formation": "Harami",
      "current": null,
      "change": null,
      "grafikUrl": null
    },
    {
      "ticker": "LRSHO",
      "alis": "3.3950",
      "stop": "3.3200",
      "risk": "2.21",
      "formation": "Harami",
      "current": null,
      "change": null,
      "grafikUrl": null
    },
    {
      "ticker": "ADEL",
      "alis": "32.58",
      "stop": "31.86",
      "risk": "2.21",
      "formation": "Harami",
      "current": null,
      "change": null,
      "grafikUrl": null
    },
    {
      "ticker": "SEKFK",
      "alis": "10.28",
      "stop": "10.05",
      "risk": "2.24",
      "formation": "Harami",
      "current": null,
      "change": null,
      "grafikUrl": null
    },
    {
      "ticker": "SAHOL",
      "alis": "92.00",
      "stop": "89.90",
      "risk": "2.28",
      "formation": "Harami",
      "current": null,
      "change": null,
      "grafikUrl": null
    },
    {
      "ticker": "DMSAS",
      "alis": "8.7650",
      "stop": "8.5600",
      "risk": "2.34",
      "formation": "Harami",
      "current": null,
      "change": null,
      "grafikUrl": null
    },
    {
      "ticker": "AHGAZ",
      "alis": "31.58",
      "stop": "30.84",
      "risk": "2.34",
      "formation": "Ters Çekiç",
      "current": null,
      "change": null,
      "grafikUrl": null
    },
    {
      "ticker": "ULUUN",
      "alis": "8.4600",
      "stop": "8.2500",
      "risk": "2.48",
      "formation": "Harami",
      "current": null,
      "change": null,
      "grafikUrl": null
    },
    {
      "ticker": "MEYSU",
      "alis": "17.97",
      "stop": "17.51",
      "risk": "2.56",
      "formation": "Harami",
      "current": null,
      "change": null,
      "grafikUrl": null
    },
    {
      "ticker": "RTALB",
      "alis": "3.4800",
      "stop": "3.3900",
      "risk": "2.59",
      "formation": "Harami",
      "current": null,
      "change": null,
      "grafikUrl": null
    },
    {
      "ticker": "SNICA",
      "alis": "4.2200",
      "stop": "4.1100",
      "risk": "2.61",
      "formation": "Harami",
      "current": null,
      "change": null,
      "grafikUrl": null
    },
    {
      "ticker": "KIMMR",
      "alis": "16.76",
      "stop": "16.32",
      "risk": "2.63",
      "formation": "Delen Mumlar",
      "current": null,
      "change": null,
      "grafikUrl": null
    },
    {
      "ticker": "TERA",
      "alis": "201.80",
      "stop": "196.50",
      "risk": "2.63",
      "formation": "Harami",
      "current": null,
      "change": null,
      "grafikUrl": null
    },
    {
      "ticker": "ZPLIBF",
      "alis": "191.90",
      "stop": "186.75",
      "risk": "2.68",
      "formation": "Harami",
      "current": null,
      "change": null,
      "grafikUrl": null
    },
    {
      "ticker": "BAKAB",
      "alis": "47.56",
      "stop": "46.28",
      "risk": "2.69",
      "formation": "Delen Mumlar",
      "current": null,
      "change": null,
      "grafikUrl": null
    },
    {
      "ticker": "DERHL",
      "alis": "13.74",
      "stop": "13.37",
      "risk": "2.69",
      "formation": "Harami",
      "current": null,
      "change": null,
      "grafikUrl": null
    },
    {
      "ticker": "QNBTR",
      "alis": "221.00",
      "stop": "215.00",
      "risk": "2.71",
      "formation": "Harami",
      "current": null,
      "change": null,
      "grafikUrl": null
    },
    {
      "ticker": "YEOTK",
      "alis": "115.65",
      "stop": "112.40",
      "risk": "2.81",
      "formation": "Ters Çekiç",
      "current": null,
      "change": null,
      "grafikUrl": null
    },
    {
      "ticker": "BANVT",
      "alis": "156.00",
      "stop": "151.50",
      "risk": "2.88",
      "formation": "Yutan Boğa",
      "current": null,
      "change": null,
      "grafikUrl": null
    },
    {
      "ticker": "BARMA",
      "alis": "60.65",
      "stop": "58.90",
      "risk": "2.89",
      "formation": "Yutan Boğa",
      "current": null,
      "change": null,
      "grafikUrl": null
    },
    {
      "ticker": "KRONT",
      "alis": "20.00",
      "stop": "19.42",
      "risk": "2.90",
      "formation": "Harami",
      "current": null,
      "change": null,
      "grafikUrl": null
    },
    {
      "ticker": "INTEM",
      "alis": "275.25",
      "stop": "267.25",
      "risk": "2.91",
      "formation": "Harami",
      "current": null,
      "change": null,
      "grafikUrl": null
    },
    {
      "ticker": "CEMZY",
      "alis": "13.39",
      "stop": "13.00",
      "risk": "2.91",
      "formation": "Harami",
      "current": null,
      "change": null,
      "grafikUrl": null
    },
    {
      "ticker": "ARMGD",
      "alis": "125.70",
      "stop": "122.00",
      "risk": "2.94",
      "formation": "Yutan Boğa",
      "current": null,
      "change": null,
      "grafikUrl": null
    },
    {
      "ticker": "YYAPI",
      "alis": "1.0100",
      "stop": "0.9800",
      "risk": "2.97",
      "formation": "Yutan Boğa",
      "current": null,
      "change": null,
      "grafikUrl": null
    },
    {
      "ticker": "DCTTR",
      "alis": "12.37",
      "stop": "12.00",
      "risk": "2.99",
      "formation": "Yutan Boğa",
      "current": null,
      "change": null,
      "grafikUrl": null
    },
    {
      "ticker": "MZHLD",
      "alis": "6.1550",
      "stop": "5.9700",
      "risk": "3.01",
      "formation": "Doji",
      "current": null,
      "change": null,
      "grafikUrl": null
    },
    {
      "ticker": "ECILC",
      "alis": "87.25",
      "stop": "84.60",
      "risk": "3.04",
      "formation": "Harami",
      "current": null,
      "change": null,
      "grafikUrl": null
    },
    {
      "ticker": "KRPLS",
      "alis": "9.4900",
      "stop": "9.2000",
      "risk": "3.06",
      "formation": "Harami",
      "current": null,
      "change": null,
      "grafikUrl": null
    },
    {
      "ticker": "BINBN",
      "alis": "177.50",
      "stop": "172.00",
      "risk": "3.10",
      "formation": "Harami",
      "current": null,
      "change": null,
      "grafikUrl": null
    },
    {
      "ticker": "DYOBY",
      "alis": "17.07",
      "stop": "16.54",
      "risk": "3.10",
      "formation": "Doji",
      "current": null,
      "change": null,
      "grafikUrl": null
    },
    {
      "ticker": "ALCAR",
      "alis": "770.00",
      "stop": "746.00",
      "risk": "3.12",
      "formation": "Yutan Boğa",
      "current": null,
      "change": null,
      "grafikUrl": null
    },
    {
      "ticker": "ATEKS",
      "alis": "94.00",
      "stop": "91.00",
      "risk": "3.19",
      "formation": "Harami",
      "current": null,
      "change": null,
      "grafikUrl": null
    },
    {
      "ticker": "TUPRS",
      "alis": "240.80",
      "stop": "233.00",
      "risk": "3.24",
      "formation": "Harami",
      "current": null,
      "change": null,
      "grafikUrl": null
    },
    {
      "ticker": "GSDDE",
      "alis": "12.41",
      "stop": "12.00",
      "risk": "3.30",
      "formation": "Harami",
      "current": null,
      "change": null,
      "grafikUrl": null
    },
    {
      "ticker": "CATES",
      "alis": "40.86",
      "stop": "39.42",
      "risk": "3.52",
      "formation": "Harami",
      "current": null,
      "change": null,
      "grafikUrl": null
    },
    {
      "ticker": "SKBNK",
      "alis": "13.27",
      "stop": "12.80",
      "risk": "3.54",
      "formation": "Harami",
      "current": null,
      "change": null,
      "grafikUrl": null
    },
    {
      "ticker": "GOKNR",
      "alis": "24.52",
      "stop": "23.64",
      "risk": "3.59",
      "formation": "Harami",
      "current": null,
      "change": null,
      "grafikUrl": null
    },
    {
      "ticker": "PASEU",
      "alis": "110.50",
      "stop": "106.50",
      "risk": "3.62",
      "formation": "Harami",
      "current": null,
      "change": null,
      "grafikUrl": null
    },
    {
      "ticker": "SNPAM",
      "alis": "21.88",
      "stop": "21.06",
      "risk": "3.75",
      "formation": "Çekiç",
      "current": null,
      "change": null,
      "grafikUrl": null
    },
    {
      "ticker": "YGGYO",
      "alis": "219.10",
      "stop": "210.50",
      "risk": "3.93",
      "formation": "Harami",
      "current": null,
      "change": null,
      "grafikUrl": null
    },
    {
      "ticker": "KTSKR",
      "alis": "99.95",
      "stop": "95.95",
      "risk": "4.00",
      "formation": "Doji",
      "current": null,
      "change": null,
      "grafikUrl": null
    },
    {
      "ticker": "IZFAS",
      "alis": "66.60",
      "stop": "63.85",
      "risk": "4.13",
      "formation": "Harami",
      "current": null,
      "change": null,
      "grafikUrl": null
    },
    {
      "ticker": "EPLAS",
      "alis": "6.0300",
      "stop": "5.7800",
      "risk": "4.15",
      "formation": "Yutan Boğa",
      "current": null,
      "change": null,
      "grafikUrl": null
    },
    {
      "ticker": "GATEG",
      "alis": "306.00",
      "stop": "293.00",
      "risk": "4.25",
      "formation": "Harami",
      "current": null,
      "change": null,
      "grafikUrl": null
    },
    {
      "ticker": "UCAYM",
      "alis": "35.52",
      "stop": "34.00",
      "risk": "4.28",
      "formation": "Harami",
      "current": null,
      "change": null,
      "grafikUrl": null
    },
    {
      "ticker": "SEYKM",
      "alis": "5.0500",
      "stop": "4.8300",
      "risk": "4.36",
      "formation": "Doji",
      "current": null,
      "change": null,
      "grafikUrl": null
    },
    {
      "ticker": "KFEIN",
      "alis": "11.47",
      "stop": "10.97",
      "risk": "4.36",
      "formation": "Harami",
      "current": null,
      "change": null,
      "grafikUrl": null
    },
    {
      "ticker": "CCOLA",
      "alis": "78.80",
      "stop": "75.35",
      "risk": "4.38",
      "formation": "Delen Mumlar",
      "current": null,
      "change": null,
      "grafikUrl": null
    },
    {
      "ticker": "DZGYO",
      "alis": "8.6400",
      "stop": "8.2600",
      "risk": "4.40",
      "formation": "Harami",
      "current": null,
      "change": null,
      "grafikUrl": null
    },
    {
      "ticker": "AVPGY",
      "alis": "60.90",
      "stop": "58.22",
      "risk": "4.40",
      "formation": "Doji",
      "current": null,
      "change": null,
      "grafikUrl": null
    },
    {
      "ticker": "HOROZ",
      "alis": "69.68",
      "stop": "66.45",
      "risk": "4.64",
      "formation": "Harami",
      "current": null,
      "change": null,
      "grafikUrl": null
    },
    {
      "ticker": "TEKTU",
      "alis": "10.99",
      "stop": "10.47",
      "risk": "4.73",
      "formation": "Harami",
      "current": null,
      "change": null,
      "grafikUrl": null
    },
    {
      "ticker": "TRCAS",
      "alis": "44.72",
      "stop": "42.56",
      "risk": "4.83",
      "formation": "Harami",
      "current": null,
      "change": null,
      "grafikUrl": null
    },
    {
      "ticker": "TGSAS",
      "alis": "170.00",
      "stop": "161.70",
      "risk": "4.88",
      "formation": "Harami",
      "current": null,
      "change": null,
      "grafikUrl": null
    }
  ]
}