{
  "updatedAt": "14.04.2026 01:53:44",
  "signals": [
    {
      "ticker": "PKENT",
      "alis": "161.20",
      "stop": "160.50",
      "risk": "0.43"
    },
    {
      "ticker": "KAYSE",
      "alis": "4.6500",
      "stop": "4.6200",
      "risk": "0.65"
    },
    {
      "ticker": "BAGFS",
      "alis": "33.38",
      "stop": "32.88",
      "risk": "1.50"
    },
    {
      "ticker": "EUREN",
      "alis": "5.0100",
      "stop": "4.8900",
      "risk": "2.40"
    },
    {
      "ticker": "PINSU",
      "alis": "12.12",
      "stop": "11.82",
      "risk": "2.48"
    },
    {
      "ticker": "GEREL",
      "alis": "37.94",
      "stop": "36.80",
      "risk": "3.00"
    },
    {
      "ticker": "ARTMS",
      "alis": "43.37",
      "stop": "42.04",
      "risk": "3.07"
    },
    {
      "ticker": "ISGSY",
      "alis": "127.70",
      "stop": "123.60",
      "risk": "3.21"
    },
    {
      "ticker": "ECOGR",
      "alis": "35.83",
      "stop": "34.58",
      "risk": "3.49"
    },
    {
      "ticker": "GENIL",
      "alis": "10.47",
      "stop": "10.10",
      "risk": "3.53"
    },
    {
      "ticker": "KLRHO",
      "alis": "107.00",
      "stop": "103.10",
      "risk": "3.64"
    },
    {
      "ticker": "DESA",
      "alis": "13.30",
      "stop": "12.80",
      "risk": "3.76"
    },
    {
      "ticker": "AKFIS",
      "alis": "44.89",
      "stop": "43.16",
      "risk": "3.85"
    },
    {
      "ticker": "KRONT",
      "alis": "20.60",
      "stop": "19.59",
      "risk": "4.90"
    }
  ]
}